blueetl_core/__init__.py
blueetl_core/_version.py
blueetl_core/constants.py
blueetl_core/etl.py
blueetl_core/logging.py
blueetl_core/parallel.py
blueetl_core/utils.py
blueetl_core-0.2.5.dist-info/AUTHORS.txt
blueetl_core-0.2.5.dist-info/LICENSE.txt
blueetl_core-0.2.5.dist-info/METADATA
blueetl_core-0.2.5.dist-info/WHEEL
blueetl_core-0.2.5.dist-info/top_level.txt
blueetl_core-0.2.5.dist-info/RECORD
