Metadata-Version: 2.1
Name: blueetl-core
Version: 0.2.5
Summary: Core transformations for BlueETL
Author: Blue Brain Project, EPFL
License: Apache-2.0
Project-URL: Homepage, https://github.com/BlueBrain/blueetl-core
Project-URL: Repository, https://github.com/BlueBrain/blueetl-core.git
Project-URL: Documentation, https://blueetl-core.readthedocs.io/
Project-URL: Tracker, https://github.com/BlueBrain/blueetl-core/issues
Classifier: Development Status :: 2 - Pre-Alpha
Classifier: Intended Audience :: Education
Classifier: Intended Audience :: Science/Research
Classifier: Programming Language :: Python
Classifier: Programming Language :: Python :: 3
Classifier: Programming Language :: Python :: 3.9
Classifier: Programming Language :: Python :: 3.10
Classifier: Programming Language :: Python :: 3.11
Classifier: Programming Language :: Python :: 3.12
Classifier: Topic :: Scientific/Engineering :: Bio-Informatics
Requires-Python: >=3.9
License-File: LICENSE.txt
License-File: AUTHORS.txt
Requires-Dist: numpy>=1.19.4
Requires-Dist: pandas>=1.3.0
Requires-Dist: joblib>=1.3.1
Requires-Dist: packaging>=21.3
Provides-Extra: docs
Requires-Dist: sphinx; extra == "docs"
Requires-Dist: sphinx-bluebrain-theme; extra == "docs"
